cypari/__init__.py
cypari/_pari.cpython-313-aarch64-linux-gnu.so
cypari/memory.py
cypari/py2tests.py
cypari/py3tests.py
cypari/test.py
cypari/tests.py
cypari/version.py
cypari-2.5.6.dist-info/METADATA
cypari-2.5.6.dist-info/WHEEL
cypari-2.5.6.dist-info/top_level.txt
cypari-2.5.6.dist-info/RECORD
