Metadata-Version: 2.4
Name: cypari
Version: 2.5.6
Summary: Sage's PARI extension, modified to stand alone.
Home-page: https://bitbucket.org/t3m/cypari
Author: Marc Culler and Nathan M. Dunfield
Author-email: culler@uic.edu, nathan@dunfield.info
License: GPLv2+
Keywords: Pari,SageMath,SnapPy
Classifier: Development Status :: 5 - Production/Stable
Classifier: Intended Audience :: Science/Research
Classifier: License :: OSI Approved :: GNU General Public License v2 or later (GPLv2+)
Classifier: Operating System :: OS Independent
Classifier: Programming Language :: C
Classifier: Programming Language :: Python
Classifier: Topic :: Scientific/Engineering :: Mathematics
Dynamic: author
Dynamic: author-email
Dynamic: classifier
Dynamic: description
Dynamic: home-page
Dynamic: keywords
Dynamic: license
Dynamic: summary
